lxf/__init__.py
lxf/ai/agents/interviewer.py
lxf/ai/classification/classifier.py
lxf/ai/classification/multiclass/common.py
lxf/ai/classification/multiclass/jupiter_model.py
lxf/ai/classification/tc_finance/accountings.py
lxf/ai/ocr/cni_ocr.py
lxf/ai/ocr/default_ocr.py
lxf/ai/ocr/iban_ocr.py
lxf/ai/ocr/ocr_pdf.py
lxf/ai/ocr/pdf_utilities.py
lxf/ai/ocr/text_extractor.py
lxf/ai/ocr/cni_utilities/recognize_zones.py
lxf/ai/ocr/cni_utilities/detection/cni_detection.py
lxf/ai/ocr/cni_utilities/detection/rois.py
lxf/ai/text_analysis/default_text_analysis.py
lxf/ai/title_analysis/correct_jsonl_prodigy.py
lxf/ai/title_analysis/extract_titles_with_format.py
lxf/ai/title_analysis/prepare_title_dataset.py
lxf/converters/converter.py
lxf/domain/TrainingData.py
lxf/domain/cni.py
lxf/domain/cni_zones.py
lxf/domain/entity.py
lxf/domain/extracted_data.py
lxf/domain/iban.py
lxf/domain/inference_result.py
lxf/domain/keyWord.py
lxf/domain/keyphrase.py
lxf/domain/keyswordsandphrases.py
lxf/domain/loan.py
lxf/domain/loan_proposal.py
lxf/domain/medicaments.py
lxf/domain/predictions.py
lxf/domain/repertoire.py
lxf/domain/tables.py
lxf/extractors/administratif/cni_extractor.py
lxf/extractors/administratif/urbanisme/cu_extractor.py
lxf/extractors/default/default_extractor.py
lxf/extractors/finance/iban_extractor.py
lxf/extractors/finance/odp_extractor.py
lxf/extractors/finance/odp_proposal_extractor.py
lxf/extractors/finance/ibans/iban_analyzer.py
lxf/extractors/finance/loans/loan_extracted_data.py
lxf/extractors/finance/loans/loan_extractor.py
lxf/extractors/finance/loans/loan_proposal_extractor.py
lxf/extractors/metier/notariat/__init__.py
lxf/extractors/metier/notariat/repertoire/repertoire_extractor.py
lxf/repositories/training_repository.py
lxf/services/keys_words.py
lxf/services/measure_time.py
lxf/services/pdf.py
lxf/services/try_safe.py
lxf/settings/__init__.py
lxf/utilities/tables_helper.py
lxf/utilities/text_comparator.py
lxf/utilities/text_utils.py
pylexfluent-0.1.74.dist-info/METADATA
pylexfluent-0.1.74.dist-info/WHEEL
pylexfluent-0.1.74.dist-info/licenses/LICENSE
pylexfluent-0.1.74.dist-info/RECORD
