Metadata-Version: 2.4
Name: pylexfluent
Version: 0.1.74
Summary: Librairie outils IA Lexia par Lexfluent
Project-URL: Homepage, https://dev.azure.com/LexFluent2020/RevolutionAI
Project-URL: Issues, https://dev.azure.com/LexFluent2020/RevolutionAI/_queries/query/180a1ed2-3494-42cc-8d8a-2e60217c2171/
Author-email: Jacques MASSA <jacques.massa@lexfluent.com>
License-File: LICENSE
Classifier: License :: OSI Approved :: MIT License
Classifier: Operating System :: OS Independent
Classifier: Programming Language :: Python :: 3
Requires-Python: >=3.12
Requires-Dist: docling[all]
Requires-Dist: easyocr
Requires-Dist: img2pdf
Requires-Dist: jax==0.4.38
Requires-Dist: jaxlib==0.4.38
Requires-Dist: langchain-community
Requires-Dist: langchain-ollama
Requires-Dist: matplotlib
Requires-Dist: mediapipe
Requires-Dist: ocrmypdf
Requires-Dist: opencv-python
Requires-Dist: openpyxl
Requires-Dist: pandas
Requires-Dist: pdf2image
Requires-Dist: pdfplumber
Requires-Dist: pillow>=10.1.0
Requires-Dist: pymongo
Requires-Dist: pytesseract
Requires-Dist: scikit-learn
Requires-Dist: sentence-transformers
Requires-Dist: sentencepiece
Requires-Dist: setuptools
Requires-Dist: spacy[cuda12x]
Requires-Dist: tensorflow
Requires-Dist: tensorflow-hub
Requires-Dist: tensorrt
Requires-Dist: tensorrt-dispatch
Requires-Dist: tensorrt-lean
Requires-Dist: tf-keras
Requires-Dist: torch
Requires-Dist: torchaudio
Requires-Dist: torchvision
Requires-Dist: tqdm
Requires-Dist: transformers
Requires-Dist: wheel
